README.md
setup.py
marshmallow_advanced/__init__.py
marshmallow_advanced.egg-info/PKG-INFO
marshmallow_advanced.egg-info/SOURCES.txt
marshmallow_advanced.egg-info/dependency_links.txt
marshmallow_advanced.egg-info/not-zip-safe
marshmallow_advanced.egg-info/requires.txt
marshmallow_advanced.egg-info/top_level.txt
marshmallow_advanced/fields/__init__.py
marshmallow_advanced/fields/active.py
marshmallow_advanced/fields/instance.py
tests/__init__.py
tests/model.py
tests/test_case.py
tests/fields/__init__.py
tests/fields/active.py
tests/fields/instance.py