Metadata-Version: 2.1
Name: marshmallow-advanced
Version: 1.2.0
Summary: Lib marshmallow advanced
Home-page: https://github.com/maximshumilo/marshmallow_advanced
Author: Shumilo Maksim
Author-email: shumilo.mk@gmail.com
License: UNKNOWN
Platform: UNKNOWN
Classifier: Development Status :: 3 - Alpha
Classifier: Programming Language :: Python :: 3.8
Classifier: Intended Audience :: Developers
Classifier: Topic :: Software Development
Classifier: License :: OSI Approved :: MIT License
Classifier: Operating System :: OS Independent
Requires-Python: >=3.8
